ntutil/__init__.py
ntutil/asyncio.py
ntutil/dictionary.py
ntutil/json.py
ntutil/kalman.py
ntutil/math.py
ntutil/numpy.py
ntutil/tornado.py
ntutil-0.1.13.dist-info/METADATA
ntutil-0.1.13.dist-info/WHEEL
ntutil-0.1.13.dist-info/top_level.txt
ntutil-0.1.13.dist-info/RECORD
