Metadata-Version: 2.1
Name: ntutil
Version: 0.1.13
Summary: Novianto Python utilities
Home-page: https://open.novianto.tech
Author: Rony Novianto
Author-email: rony@novianto.tech
License: MIT
Keywords: Novianto Python Utilities
Platform: UNKNOWN
